gfetch/app.py
gfetch/auth.py
gfetch/emails.py
gfetch/scratch.py
gfetch_cli-0.1.1.dist-info/licenses/LICENSE
gfetch_cli-0.1.1.dist-info/METADATA
gfetch_cli-0.1.1.dist-info/WHEEL
gfetch_cli-0.1.1.dist-info/entry_points.txt
gfetch_cli-0.1.1.dist-info/top_level.txt
gfetch_cli-0.1.1.dist-info/RECORD
