Metadata-Version: 2.4
Name: gfetch-cli
Version: 0.1.1
Summary: A CLI app to back up your gmail emails locally
Author-email: Jeff Jacobson <jeffjacobsonhimself@gmail.com>
License:                     GNU GENERAL PUBLIC LICENSE
Project-URL: Homepage, https://github.com/jwjacobson/gfetch-cli
Project-URL: Issues, https://github.com/jwjacobson/gfetch-cli/issues
Requires-Python: >=3.13
License-File: LICENSE
Requires-Dist: google-api-python-client>=2.176.0
Requires-Dist: google-auth>=2.40.3
Requires-Dist: google-auth-httplib2>=0.2.0
Requires-Dist: google-auth-oauthlib>=1.2.2
Requires-Dist: python-decouple>=3.8
Dynamic: license-file
